rusta_scraper/__init__.py
rusta_scraper/requirements.txt
rusta_scraper/external_data_loader/__main__.py
rusta_scraper/external_data_loader/constants.py
rusta_scraper/external_data_loader/opti_api.py
rusta_scraper/external_data_loader/pim_api.py
rusta_scraper/snow_flake/query_loader.py
rusta_scraper/snow_flake/snowflake_connection.py
rusta_scraper/snow_flake/config/db_config.json
rusta_scraper/spider/items.py
rusta_scraper/spider/middlewares.py
rusta_scraper/spider/pipelines.py
rusta_scraper/spider/settings.py
rusta_scraper/spider/files/constants.py
rusta_scraper/spider/spiders/rusta_spider.py
rusta_scraper/spider/sql/all_active_articles_de.sql
rusta_scraper/spider/sql/all_active_articles_fi.sql
rusta_scraper/spider/sql/all_active_articles_no.sql
rusta_scraper/spider/sql/all_active_articles_se.sql
rusta_scraper/spider/sql/campaign_of_the_week.sql
rusta_scraper/spider/sql/package_price.sql
rusta_scraper/spider/sql/rolling_campaigns.sql
rusta_scraper/spider/tests/spider_factory.py
rusta_scraper/spider/tests/test_rusta_spider.py
rusta_scraper/spider/tools/__init__.py
rusta_scraper/spider/tools/logger.py
rusta_scraper/spider_factory/__main__.py
rusta_scraper/spider_factory/spider_factory.py
rusta_scraper-0.0.9.dist-info/licenses/LICENSE
rusta_scraper-0.0.9.dist-info/METADATA
rusta_scraper-0.0.9.dist-info/WHEEL
rusta_scraper-0.0.9.dist-info/top_level.txt
rusta_scraper-0.0.9.dist-info/RECORD
