Metadata-Version: 2.4
Name: rusta_scraper
Version: 0.0.9
Summary: Rusta Article Scraper
Author-email: David Momeni <dav.momeni@gmail.com>
Requires-Python: >=3.8
License-File: LICENSE
Dynamic: license-file
